{
  "date": "2026-04-30",
  "title": "Hermes Birkin 35 (Togo Leather 2024)",
  "description": "A hand-stitched French leather handbag with a multi-year waitlist. Retail price new from Hermes boutique.",
  "image_url": "https://upload.wikimedia.org/wikipedia/commons/0/0d/Hermes_Birkin_bag.jpg",
  "answer_price": 11400.0,
  "category": "luxury",
  "year": 2024,
  "price_context": "Birkins have outperformed the S&P 500 over the last 35 years as an investment asset.",
  "source_url": "https://en.wikipedia.org/wiki/Birkin_bag"
}